django_s3_sqlite/__init__.py
django_s3_sqlite/base.py
django_s3_sqlite/client.py
django_s3_sqlite/features.py
django_s3_sqlite/management/__init__.py
django_s3_sqlite/management/commands/__init__.py
django_s3_sqlite/management/commands/create_admin_user.py
django_s3_sqlite/management/commands/s3_sqlite_vacuum.py
django_s3_sqlite/migrations/__init__.py
django_s3_sqlite-0.0.5.dist-info/METADATA
django_s3_sqlite-0.0.5.dist-info/WHEEL
django_s3_sqlite-0.0.5.dist-info/top_level.txt
django_s3_sqlite-0.0.5.dist-info/RECORD
